{
  "policy_id": "demo-dry-run-video",
  "target_node": "jetson-a",
  "interface": "eth0",
  "mode": "dry-run",
  "backend": "simple",
  "root_rate_mbit": 50,
  "safety": {
    "dry_run": true,
    "auto_rollback_seconds": 60,
    "require_confirm": true,
    "allow_ssh_interface": false
  },
  "default": {
    "bandwidth_mbit": 20,
    "priority": 7
  },
  "rules": [
    {
      "name": "video-flow",
      "match": {
        "dst_ip": "JETSON_B_IP",
        "dst_port": 5000,
        "protocol": "udp"
      },
      "bandwidth_mbit": 8,
      "delay_ms": 30,
      "loss_percent": 0.0,
      "priority": 1
    }
  ]
}
